[
  {
    "type": "console.flag/model",
    "properties": {
      "flag": "TRUSTEE_TRUSTEECONFIG",
      "model": {
        "group": "confidentialcontainers.org",
        "version": "v1alpha1",
        "kind": "TrusteeConfig"
      }
    }
  },
  {
    "type": "console.model-metadata",
    "properties": {
      "model": {
        "group": "confidentialcontainers.org",
        "version": "v1alpha1",
        "kind": "TrusteeConfig"
      },
      "abbr": "TC",
      "label": "TrusteeConfig",
      "labelPlural": "TrusteeConfigs",
      "color": "#6753ac"
    }
  },
  {
    "type": "console.model-metadata",
    "properties": {
      "model": {
        "group": "confidentialcontainers.org",
        "version": "v1alpha1",
        "kind": "KbsConfig"
      },
      "abbr": "KBS",
      "label": "KbsConfig",
      "labelPlural": "KbsConfigs",
      "color": "#6753ac"
    }
  },

  {
    "type": "console.navigation/section",
    "properties": {
      "id": "trustee",
      "perspective": "admin",
      "name": "%plugin__trustee-openshift-console-plugin~Confidential Attestation%",
      "insertAfter": "confidential-containers"
    }
  },
  {
    "type": "console.navigation/href",
    "properties": {
      "id": "trustee-overview",
      "perspective": "admin",
      "section": "trustee",
      "name": "%plugin__trustee-openshift-console-plugin~Overview%",
      "href": "/trustee"
    },
    "flags": { "required": ["TRUSTEE_TRUSTEECONFIG"] }
  },
  {
    "type": "console.navigation/href",
    "properties": {
      "id": "trustee-deploy",
      "perspective": "admin",
      "section": "trustee",
      "name": "%plugin__trustee-openshift-console-plugin~Setup%",
      "href": "/trustee/setup"
    }
  },
  {
    "type": "console.navigation/href",
    "properties": {
      "id": "trustee-topology",
      "perspective": "admin",
      "section": "trustee",
      "name": "%plugin__trustee-openshift-console-plugin~Attestation topology%",
      "href": "/trustee/topology"
    },
    "flags": { "required": ["TRUSTEE_TRUSTEECONFIG"] }
  },
  {
    "type": "console.navigation/href",
    "properties": {
      "id": "trustee-activity",
      "perspective": "admin",
      "section": "trustee",
      "name": "%plugin__trustee-openshift-console-plugin~Attestation activity%",
      "href": "/trustee/activity"
    },
    "flags": { "required": ["TRUSTEE_TRUSTEECONFIG"] }
  },
  {
    "type": "console.navigation/href",
    "properties": {
      "id": "trustee-configs",
      "perspective": "admin",
      "section": "trustee",
      "name": "%plugin__trustee-openshift-console-plugin~TrusteeConfig%",
      "href": "/trustee/config"
    },
    "flags": { "required": ["TRUSTEE_TRUSTEECONFIG"] }
  },
  {
    "type": "console.page/route",
    "properties": {
      "exact": true,
      "path": "/trustee/config",
      "component": { "$codeRef": "TrusteeConfigRedirect" }
    },
    "flags": { "required": ["TRUSTEE_TRUSTEECONFIG"] }
  },
  {
    "type": "console.page/route",
    "properties": {
      "exact": true,
      "path": "/trustee",
      "component": { "$codeRef": "TrusteeAttestation" }
    },
    "flags": { "required": ["TRUSTEE_TRUSTEECONFIG"] }
  },
  {
    "type": "console.page/route",
    "properties": {
      "exact": true,
      "path": "/trustee/topology",
      "component": { "$codeRef": "TrusteeTopology" }
    },
    "flags": { "required": ["TRUSTEE_TRUSTEECONFIG"] }
  },
  {
    "type": "console.page/route",
    "properties": {
      "exact": true,
      "path": "/trustee/activity",
      "component": { "$codeRef": "TrusteeActivity" }
    },
    "flags": { "required": ["TRUSTEE_TRUSTEECONFIG"] }
  },
  {
    "type": "console.page/route",
    "properties": {
      "exact": true,
      "path": "/trustee/setup",
      "component": { "$codeRef": "DeployTrusteeWizard" }
    }
  },
  {
    "type": "console.tab/horizontalNav",
    "properties": {
      "model": {
        "group": "confidentialcontainers.org",
        "version": "v1alpha1",
        "kind": "TrusteeConfig"
      },
      "page": {
        "name": "%plugin__trustee-openshift-console-plugin~Policies%",
        "href": "policies"
      },
      "component": { "$codeRef": "TrusteePoliciesTab" }
    },
    "flags": { "required": ["TRUSTEE_TRUSTEECONFIG"] }
  },
  {
    "type": "console.tab/horizontalNav",
    "properties": {
      "model": {
        "group": "confidentialcontainers.org",
        "version": "v1alpha1",
        "kind": "TrusteeConfig"
      },
      "page": {
        "name": "%plugin__trustee-openshift-console-plugin~Reference values%",
        "href": "reference-values"
      },
      "component": { "$codeRef": "TrusteeReferenceValuesTab" }
    },
    "flags": { "required": ["TRUSTEE_TRUSTEECONFIG"] }
  },
  {
    "type": "console.tab/horizontalNav",
    "properties": {
      "model": {
        "group": "confidentialcontainers.org",
        "version": "v1alpha1",
        "kind": "TrusteeConfig"
      },
      "page": {
        "name": "%plugin__trustee-openshift-console-plugin~Initdata%",
        "href": "initdata"
      },
      "component": { "$codeRef": "TrusteeInitdataTab" }
    },
    "flags": { "required": ["TRUSTEE_TRUSTEECONFIG"] }
  },
  {
    "type": "console.tab/horizontalNav",
    "properties": {
      "model": {
        "group": "confidentialcontainers.org",
        "version": "v1alpha1",
        "kind": "TrusteeConfig"
      },
      "page": {
        "name": "%plugin__trustee-openshift-console-plugin~Delivered secrets%",
        "href": "secrets"
      },
      "component": { "$codeRef": "TrusteeSecretsTab" }
    },
    "flags": { "required": ["TRUSTEE_TRUSTEECONFIG"] }
  },
  {
    "type": "console.tab/horizontalNav",
    "properties": {
      "model": {
        "group": "confidentialcontainers.org",
        "version": "v1alpha1",
        "kind": "TrusteeConfig"
      },
      "page": {
        "name": "%plugin__trustee-openshift-console-plugin~GPU attestation%",
        "href": "gpu-attestation"
      },
      "component": { "$codeRef": "TrusteeGpuTab" }
    },
    "flags": { "required": ["TRUSTEE_TRUSTEECONFIG"] }
  },
  {
    "type": "console.tab/horizontalNav",
    "properties": {
      "model": {
        "group": "confidentialcontainers.org",
        "version": "v1alpha1",
        "kind": "TrusteeConfig"
      },
      "page": {
        "name": "%plugin__trustee-openshift-console-plugin~Health%",
        "href": "health"
      },
      "component": { "$codeRef": "TrusteeHealthTab" }
    },
    "flags": { "required": ["TRUSTEE_TRUSTEECONFIG"] }
  },
  {
    "type": "console.action/resource-provider",
    "properties": {
      "model": { "version": "v1", "kind": "Pod" },
      "provider": { "$codeRef": "ccActions.useCcPodActions" }
    },
    "flags": { "required": ["TRUSTEE_TRUSTEECONFIG"] }
  }
]
